voice_bot_demo/__init__.py
voice_bot_demo/__main__.py
voice_bot_demo/cli.py
voice_bot_demo/console.py
voice_bot_demo/utils.py
voice_bot_demo/speech_text/__init__.py
voice_bot_demo/speech_text/assembly.py
voice_bot_demo/speech_text/interface.py
voice_bot_demo/speech_text/whisper.py
voice_bot_demo/text_speech/__init__.py
voice_bot_demo/text_speech/gpt_pyttsx3.py
voice_bot_demo/text_speech/interface.py
voice_bot_demo/text_speech/tts.py
voice_bot_demo-0.2.dist-info/LICENSE
voice_bot_demo-0.2.dist-info/METADATA
voice_bot_demo-0.2.dist-info/WHEEL
voice_bot_demo-0.2.dist-info/entry_points.txt
voice_bot_demo-0.2.dist-info/top_level.txt
voice_bot_demo-0.2.dist-info/RECORD
