Metadata-Version: 2.1
Name: voice-bot-demo
Version: 0.2
Summary: AI conversational bot
Home-page: https://github.com/helloworld/voice-bot-demo
Author: Sashank Thupukari
License: Apache License, Version 2.0
Project-URL: Issues, https://github.com/helloworld/voice-bot-demo/issues
Project-URL: CI, https://github.com/helloworld/voice-bot-demo/actions
Project-URL: Changelog, https://github.com/helloworld/voice-bot-demo/releases
Requires-Python: >=3.7
License-File: LICENSE
Requires-Dist: click
Requires-Dist: rich
Requires-Dist: pyaudio
Requires-Dist: websockets
Requires-Dist: openai
Requires-Dist: pyttsx3
Provides-Extra: black
Requires-Dist: black ; extra == 'black'
Provides-Extra: pyright
Requires-Dist: pyright ; extra == 'pyright'
Provides-Extra: ruff
Requires-Dist: ruff ; extra == 'ruff'
Provides-Extra: test
Requires-Dist: pytest ; extra == 'test'
